{"version": 0.6, "generator": "Overpass API 0.7.62.11 87bfad18", "osm3s": {"timestamp_osm_base": "2026-04-15T22:55:46Z", "copyright": "The data included in this document is from www.openstreetmap.org. The data is made available under ODbL."}, "elements": [{"type": "node", "id": 3753829093, "lat": 38.7899608, "lon": -80.2583938, "tags": {"man_made": "tower", "tower:type": "communication"}}, {"type": "node", "id": 3773213583, "lat": 38.7416015, "lon": -80.3645936, "tags": {"man_made": "tower", "tower:type": "communication"}}, {"type": "node", "id": 3773213658, "lat": 38.7484464, "lon": -80.3630392, "tags": {"man_made": "tower", "tower:type": "communication"}}, {"type": "node", "id": 4696926094, "lat": 38.5963296, "lon": -80.3982295, "tags": {"communication:mobile_phone": "yes", "man_made": "mast", "tower:construction": "lattice", "tower:type": "communication"}}, {"type": "node", "id": 5077085978, "lat": 38.6886974, "lon": -79.9790914, "tags": {"communication:mobile_phone": "yes", "man_made": "mast", "tower:construction": "lattice", "tower:type": "communication"}}, {"type": "node", "id": 10706036421, "lat": 38.8997173, "lon": -80.010544}, {"type": "node", "id": 10706036422, "lat": 38.8996868, "lon": -80.0106637}, {"type": "node", "id": 10706036423, "lat": 38.8997744, "lon": -80.0106195}, {"type": "node", "id": 10706425609, "lat": 38.9047689, "lon": -79.9981623}, {"type": "node", "id": 10706425610, "lat": 38.904758, "lon": -79.9980319}, {"type": "node", "id": 10706425611, "lat": 38.9048415, "lon": -79.9981043}, {"type": "node", "id": 11902531273, "lat": 38.8502891, "lon": -80.3277308, "tags": {"communication:mobile_phone": "yes", "man_made": "mast", "tower:construction": "guyed_lattice", "tower:type": "communication"}}, {"type": "node", "id": 12038620463, "lat": 38.509969, "lon": -80.3421749, "tags": {"communication:microwave": "yes", "description": "Former AT&T LongLines site.", "man_made": "tower", "tower:construction": "lattice", "tower:type": "communication"}}, {"type": "node", "id": 12752453796, "lat": 38.9032696, "lon": -80.2310284, "tags": {"communication:mobile_phone": "yes", "man_made": "mast", "tower:construction": "guyed_lattice", "tower:type": "communication"}}, {"type": "node", "id": 12752480306, "lat": 38.8914476, "lon": -80.3081669, "tags": {"communication:mobile_phone": "yes", "man_made": "mast", "tower:construction": "lattice", "tower:type": "communication"}}, {"type": "node", "id": 13481921572, "lat": 38.663993, "lon": -80.2942582, "tags": {"communication:mobile_phone": "yes", "man_made": "mast", "tower:type": "communication"}}, {"type": "way", "id": 1150889066, "nodes": [10706036423, 10706036422, 10706036421, 10706036423], "tags": {"communication:radio": "yes", "man_made": "mast", "tower:construction": "lattice", "tower:type": "communication"}}, {"type": "way", "id": 1150912293, "nodes": [10706425611, 10706425610, 10706425609, 10706425611], "tags": {"communication:mobile_phone": "yes", "man_made": "mast", "tower:construction": "lattice", "tower:type": "communication"}}]}